pytest_reqyaml/__init__.py
pytest_reqyaml/plugin.py
pytest_reqyaml/ReqyamlError.py
pytest_reqyaml/test_request.yaml
pytest_reqyaml-0.1.41.dist-info/entry_points.txt
pytest_reqyaml-0.1.41.dist-info/METADATA
pytest_reqyaml-0.1.41.dist-info/WHEEL
pytest_reqyaml-0.1.41.dist-info/RECORD
